sql_runner/core.py
sql_runner/psycopg3_runner.py
sql_runner/trino_runner.py
sql_runner/utils.py
py_sql_runner-0.1.0.dist-info/METADATA
py_sql_runner-0.1.0.dist-info/WHEEL
py_sql_runner-0.1.0.dist-info/top_level.txt
py_sql_runner-0.1.0.dist-info/RECORD
